clap/__init__.py
clap/embedding/__init__.py
clap/embedding/base_embedding.py
clap/embedding/fastembed_embedding.py
clap/embedding/ollama_embedding.py
clap/embedding/sentence_transformer_embedding.py
clap/llm_services/__init__.py
clap/llm_services/base.py
clap/llm_services/google_openai_compat_service.py
clap/llm_services/groq_service.py
clap/llm_services/ollama_service.py
clap/mcp_client/__init__.py
clap/mcp_client/client.py
clap/multiagent_pattern/__init__.py
clap/multiagent_pattern/agent.py
clap/multiagent_pattern/team.py
clap/react_pattern/__init__.py
clap/react_pattern/react_agent.py
clap/tool_pattern/__init__.py
clap/tool_pattern/tool.py
clap/tool_pattern/tool_agent.py
clap/tools/__init__.py
clap/tools/email_tools.py
clap/tools/web3_tools.py
clap/tools/web_crawler.py
clap/tools/web_search.py
clap/utils/__init__.py
clap/utils/completions.py
clap/utils/extraction.py
clap/utils/logging.py
clap/utils/rag_utils.py
clap/vector_stores/__init__.py
clap/vector_stores/base.py
clap/vector_stores/chroma_store.py
clap/vector_stores/qdrant_store.py
clap_agents-0.3.2.dist-info/METADATA
clap_agents-0.3.2.dist-info/WHEEL
clap_agents-0.3.2.dist-info/licenses/LICENSE
clap_agents-0.3.2.dist-info/RECORD
