Metadata-Version: 2.4
Name: clap-agents
Version: 0.3.2
Summary: A Python framework for building cognitive agentic patterns including ReAct agents, Multi-Agent Teams, native tool calling, and MCP client integration.
Project-URL: Homepage, https://github.com/MaitreyaM/CLAP-AGENTS.git
Project-URL: Repository, https://github.com/MaitreyaM/CLAP-AGENTS.git
Project-URL: Issues, https://github.com/MaitreyaM/CLAP-AGENTS.git/issues
Author-email: Maitreya Mishra <maitreyamishra04@gmail.com>
License: 
License-File: LICENSE
Keywords: agent,agentic,agentic systems,ai,framework,llm,mcp,multi-agent,react,tool calling
Classifier: Development Status :: 3 - Alpha
Classifier: Intended Audience :: Developers
Classifier: License :: OSI Approved :: Apache Software License
Classifier: Operating System :: OS Independent
Classifier: Programming Language :: Python :: 3
Classifier: Programming Language :: Python :: 3.10
Classifier: Programming Language :: Python :: 3.11
Classifier: Programming Language :: Python :: 3.12
Classifier: Topic :: Scientific/Engineering :: Artificial Intelligence
Classifier: Topic :: Software Development :: Libraries :: Application Frameworks
Requires-Python: >=3.10
Requires-Dist: anyio>=4.5
Requires-Dist: colorama
Requires-Dist: duckduckgo-search
Requires-Dist: groq
Requires-Dist: httpx-sse>=0.4
Requires-Dist: httpx>=0.27
Requires-Dist: jsonschema
Requires-Dist: mcp>=1.2.0
Requires-Dist: openai>=1.0.0
Requires-Dist: pydantic<3.0.0,>=2.7.2
Requires-Dist: requests
Provides-Extra: all
Requires-Dist: chromadb>=0.5.0; extra == 'all'
Requires-Dist: crawl4ai; extra == 'all'
Requires-Dist: fastembed>=0.2.0; extra == 'all'
Requires-Dist: graphviz; extra == 'all'
Requires-Dist: ollama>=0.2.0; extra == 'all'
Requires-Dist: pandas; extra == 'all'
Requires-Dist: pypdf; extra == 'all'
Requires-Dist: qdrant-client[fastembed]>=1.7.0; extra == 'all'
Requires-Dist: sentence-transformers; extra == 'all'
Requires-Dist: tf-keras; extra == 'all'
Requires-Dist: web3<8.0.0,>=7.12.0; extra == 'all'
Provides-Extra: chromadb
Requires-Dist: chromadb>=0.5.0; extra == 'chromadb'
Provides-Extra: fastembed
Requires-Dist: fastembed>=0.2.0; extra == 'fastembed'
Provides-Extra: ollama
Requires-Dist: ollama>=0.2.0; extra == 'ollama'
Provides-Extra: pandas
Requires-Dist: pandas; extra == 'pandas'
Provides-Extra: pdf
Requires-Dist: pypdf; extra == 'pdf'
Provides-Extra: qdrant
Requires-Dist: qdrant-client[fastembed]>=1.7.0; extra == 'qdrant'
Provides-Extra: rag
Requires-Dist: chromadb>=0.5.0; extra == 'rag'
Requires-Dist: fastembed>=0.2.0; extra == 'rag'
Requires-Dist: ollama>=0.2.0; extra == 'rag'
Requires-Dist: pypdf; extra == 'rag'
Requires-Dist: qdrant-client[fastembed]>=1.7.0; extra == 'rag'
Requires-Dist: sentence-transformers; extra == 'rag'
Requires-Dist: tf-keras; extra == 'rag'
Provides-Extra: sentence-transformers
Requires-Dist: sentence-transformers; extra == 'sentence-transformers'
Requires-Dist: tf-keras; extra == 'sentence-transformers'
Provides-Extra: standard-tools
Requires-Dist: crawl4ai; extra == 'standard-tools'
Provides-Extra: viz
Requires-Dist: graphviz; extra == 'viz'
Provides-Extra: web3
Requires-Dist: web3<8.0.0,>=7.12.0; extra == 'web3'
